<?xml version="1.0" encoding="UTF-8"?><r:RDF xmlns:r="http://www.w3.org/1999/02/22-rdf-syntax-ns#" xmlns:rdf="http://www.w3.org/1999/02/22-rdf-syntax-ns#" xmlns:s="http://www.w3.org/2004/02/skos/core#" xmlns:skos="http://www.w3.org/2004/02/skos/core#" xmlns:rs="http://www.w3.org/2000/01/rdf-schema#" xml:base="http://www.cch.kcl.ac.uk/ncse/dmvi/AL_cch_dmvi_skos.rdf"><s:Concept r:about="id:dmvi:d2e2" r:label="periods"><s:narrower><s:orderedCollection><s:memberList r:parseType="Collection"><s:Concept r:about="id:dmvi:d2e4" r:label="centuries"><s:narrower><s:orderedCollection><s:memberList r:parseType="Collection"><s:Concept r:about="id:dmvi:d2e6" r:label="sixteenth century"/><s:Concept r:about="id:dmvi:d2e12" r:label="seventeenth century"/><s:Concept r:about="id:dmvi:d2e18" r:label="eighteenth century"/><s:Concept r:about="id:dmvi:d2e24" r:label="nineteenth century"/></s:memberList></s:orderedCollection></s:narrower></s:Concept><s:Concept r:about="id:dmvi:d2e28" r:label="eras"><s:narrower><s:orderedCollection><s:memberList r:parseType="Collection"><s:Concept r:about="id:dmvi:d2e30" r:label="Greek--Roman classical"/><s:Concept r:about="id:dmvi:d2e36" r:label="Biblical"/><s:Concept r:about="id:dmvi:d2e42" r:label="Medieval"/><s:Concept r:about="id:dmvi:d2e48" r:label="Renaissance"/></s:memberList></s:orderedCollection></s:narrower></s:Concept></s:memberList></s:orderedCollection></s:narrower></s:Concept><s:Concept r:about="id:dmvi:d2e69" r:label="geography"><s:narrower><s:orderedCollection><s:memberList r:parseType="Collection"><s:Concept r:about="id:dmvi:d2e71" r:label="Great Britain"><s:narrower><s:orderedCollection><s:memberList r:parseType="Collection"><s:Concept r:about="id:dmvi:d2e73" r:label="Britain [non-specific area]"/><s:Concept r:about="id:dmvi:d2e79" r:label="England"><s:narrower><s:orderedCollection><s:memberList r:parseType="Collection"><s:Concept r:about="id:dmvi:d2e81" r:label="England [non-specific area]"/><s:Concept r:about="id:dmvi:d2e97" r:label="Birmingham"/><s:Concept r:about="id:dmvi:d2e113" r:label="Cambridge"/><s:Concept r:about="id:dmvi:d2e153" r:label="London"/><s:Concept r:about="id:dmvi:d2e162" r:label="Oxford"/><s:Concept r:about="id:dmvi:d2e186" r:label="Berkshire"/><s:Concept r:about="id:dmvi:d2e210" r:label="Derbyshire"/><s:Concept r:about="id:dmvi:d2e218" r:label="Hampshire"/><s:Concept r:about="id:dmvi:d2e323" r:label="Worcestershire"/><s:Concept r:about="id:dmvi:d2e331" r:label="Yorkshire"/></s:memberList></s:orderedCollection></s:narrower></s:Concept><s:Concept r:about="id:dmvi:d2e338" r:label="Scotland"><s:narrower><s:orderedCollection><s:memberList r:parseType="Collection"><s:Concept r:about="id:dmvi:d2e340" r:label="Scotland [non-specific area]"/><s:Concept r:about="id:dmvi:d2e348" r:label="Edinburgh"/><s:Concept r:about="id:dmvi:d2e356" r:label="Scottish Highlands"/></s:memberList></s:orderedCollection></s:narrower></s:Concept></s:memberList></s:orderedCollection></s:narrower></s:Concept><s:Concept r:about="id:dmvi:d2e384" r:label="Europe"><s:narrower><s:orderedCollection><s:memberList r:parseType="Collection"><s:Concept r:about="id:dmvi:d2e386" r:label="Europe [non-specific area]"/><s:Concept r:about="id:dmvi:d2e392" r:label="Austria"/><s:Concept r:about="id:dmvi:d2e404" r:label="France"/><s:Concept r:about="id:dmvi:d2e410" r:label="Germany"/><s:Concept r:about="id:dmvi:d2e417" r:label="Greece"/><s:Concept r:about="id:dmvi:d2e423" r:label="Ireland"/><s:Concept r:about="id:dmvi:d2e429" r:label="Italy"/><s:Concept r:about="id:dmvi:d2e435" r:label="Netherlands"/><s:Concept r:about="id:dmvi:d2e447" r:label="Russia"/><s:Concept r:about="id:dmvi:d2e453" r:label="Spain"/><s:Concept r:about="id:dmvi:d2e459" r:label="Switzerland"/><s:Concept r:about="id:dmvi:d2e465" r:label="Alps"/><s:Concept r:about="id:dmvi:d2e477" r:label="Eastern Europe"/><s:Concept r:about="id:dmvi:d2e484" r:label="Scandinavia"/></s:memberList></s:orderedCollection></s:narrower></s:Concept><s:Concept r:about="id:dmvi:d2e488" r:label="Africa"><s:narrower><s:orderedCollection><s:memberList r:parseType="Collection"><s:Concept r:about="id:dmvi:d2e490" r:label="Africa [non-specific area]"/><s:Concept r:about="id:dmvi:d2e496" r:label="Egypt"/><s:Concept r:about="id:dmvi:d2e502" r:label="South Africa"/></s:memberList></s:orderedCollection></s:narrower></s:Concept><s:Concept r:about="id:dmvi:d2e506" r:label="Asia"><s:narrower><s:orderedCollection><s:memberList r:parseType="Collection"><s:Concept r:about="id:dmvi:d2e508" r:label="Asia [non-specific area]"/><s:Concept r:about="id:dmvi:d2e514" r:label="Holy Land"/><s:Concept r:about="id:dmvi:d2e520" r:label="Middle East"/><s:Concept r:about="id:dmvi:d2e526" r:label="China"/><s:Concept r:about="id:dmvi:d2e532" r:label="India"/><s:Concept r:about="id:dmvi:d2e538" r:label="Iran"/><s:Concept r:about="id:dmvi:d2e551" r:label="Japan"/><s:Concept r:about="id:dmvi:d2e557" r:label="Sri Lanka"/></s:memberList></s:orderedCollection></s:narrower></s:Concept><s:Concept r:about="id:dmvi:d2e561" r:label="South America"><s:narrower><s:orderedCollection><s:memberList r:parseType="Collection"/></s:orderedCollection></s:narrower></s:Concept><s:Concept r:about="id:dmvi:d2e573" r:label="Central America"><s:narrower><s:orderedCollection><s:memberList r:parseType="Collection"><s:Concept r:about="id:dmvi:d2e581" r:label="Mexico"/></s:memberList></s:orderedCollection></s:narrower></s:Concept><s:Concept r:about="id:dmvi:d2e585" r:label="North America"><s:narrower><s:orderedCollection><s:memberList r:parseType="Collection"><s:Concept r:about="id:dmvi:d2e587" r:label="Canada"/><s:Concept r:about="id:dmvi:d2e593" r:label="United States of America"/></s:memberList></s:orderedCollection></s:narrower></s:Concept><s:Concept r:about="id:dmvi:d2e597" r:label="Oceania"><s:narrower><s:orderedCollection><s:memberList r:parseType="Collection"><s:Concept r:about="id:dmvi:d2e599" r:label="Australia"/><s:Concept r:about="id:dmvi:d2e605" r:label="New Zealand"/></s:memberList></s:orderedCollection></s:narrower></s:Concept></s:memberList></s:orderedCollection></s:narrower></s:Concept><s:Concept r:about="id:dmvi:d2e607" r:label="settings"><s:narrower><s:orderedCollection><s:memberList r:parseType="Collection"><s:Concept r:about="id:dmvi:d2e609" r:label="exteriors"><s:narrower><s:orderedCollection><s:memberList r:parseType="Collection"><s:Concept r:about="id:dmvi:d2e611" r:label=""/></s:memberList></s:orderedCollection></s:narrower></s:Concept><s:Concept r:about="id:dmvi:d2e615" r:label="interiors"><s:narrower><s:orderedCollection><s:memberList r:parseType="Collection"/></s:orderedCollection></s:narrower></s:Concept><s:Concept r:about="id:dmvi:d2e620" r:label="natural environments"><s:narrower><s:orderedCollection><s:memberList r:parseType="Collection"><s:Concept r:about="id:dmvi:d2e622" r:label="countryside"/><s:Concept r:about="id:dmvi:d2e628" r:label="the sea"/><s:Concept r:about="id:dmvi:d2e634" r:label="natural features"><s:narrower><s:orderedCollection><s:memberList r:parseType="Collection"><s:Concept r:about="id:dmvi:d2e636" r:label="chasms"/><s:Concept r:about="id:dmvi:d2e644" r:label="cliffs and rocks"/><s:Concept r:about="id:dmvi:d2e652" r:label="deserts"/><s:Concept r:about="id:dmvi:d2e660" r:label="glaciers"/><s:Concept r:about="id:dmvi:d2e668" r:label="hills and valleys"/><s:Concept r:about="id:dmvi:d2e676" r:label="icebergs"/><s:Concept r:about="id:dmvi:d2e684" r:label="lakes and ponds"/><s:Concept r:about="id:dmvi:d2e692" r:label="mountains"/><s:Concept r:about="id:dmvi:d2e701" r:label="plains"/><s:Concept r:about="id:dmvi:d2e709" r:label="rivers"/><s:Concept r:about="id:dmvi:d2e717" r:label="the coast"/><s:Concept r:about="id:dmvi:d2e725" r:label="waterfalls"/><s:Concept r:about="id:dmvi:d2e733" r:label="woodlands"/></s:memberList></s:orderedCollection></s:narrower></s:Concept><s:Concept r:about="id:dmvi:d2e739" r:label="celestial bodies"><s:narrower><s:orderedCollection><s:memberList r:parseType="Collection"><s:Concept r:about="id:dmvi:d2e741" r:label="moon"/><s:Concept r:about="id:dmvi:d2e749" r:label="stars"/><s:Concept r:about="id:dmvi:d2e757" r:label="sun"/></s:memberList></s:orderedCollection></s:narrower></s:Concept></s:memberList></s:orderedCollection></s:narrower></s:Concept><s:Concept r:about="id:dmvi:d2e761" r:label="built environments"><s:narrower><s:orderedCollection><s:memberList r:parseType="Collection"><s:Concept r:about="id:dmvi:d2e763" r:label="cities"/><s:Concept r:about="id:dmvi:d2e769" r:label="towns"/><s:Concept r:about="id:dmvi:d2e775" r:label="villages"/><s:Concept r:about="id:dmvi:d2e782" r:label="farms"><s:narrower><s:orderedCollection><s:memberList r:parseType="Collection"><s:Concept r:about="id:dmvi:d2e800" r:label="farmyards"/><s:Concept r:about="id:dmvi:d2e808" r:label="fields"/><s:Concept r:about="id:dmvi:d2e816" r:label="hedges"/></s:memberList></s:orderedCollection></s:narrower></s:Concept><s:Concept r:about="id:dmvi:d2e830" r:label="buildings"><s:narrower><s:orderedCollection><s:memberList r:parseType="Collection"><s:Concept r:about="id:dmvi:d2e832" r:label="arenas and stadia"/><s:Concept r:about="id:dmvi:d2e856" r:label="banks"/><s:Concept r:about="id:dmvi:d2e873" r:label="bell towers"/><s:Concept r:about="id:dmvi:d2e889" r:label="castles"/><s:Concept r:about="id:dmvi:d2e897" r:label="churches"/><s:Concept r:about="id:dmvi:d2e905" r:label="cottages"/><s:Concept r:about="id:dmvi:d2e913" r:label="factories"/><s:Concept r:about="id:dmvi:d2e929" r:label="garrisons"/><s:Concept r:about="id:dmvi:d2e962" r:label="houses"/><s:Concept r:about="id:dmvi:d2e970" r:label="huts and cabins"/><s:Concept r:about="id:dmvi:d2e986" r:label="law courts"/><s:Concept r:about="id:dmvi:d2e994" r:label="lighthouses"/><s:Concept r:about="id:dmvi:d2e1002" r:label="mansions"/><s:Concept r:about="id:dmvi:d2e1026" r:label="museums and exhibition halls"/><s:Concept r:about="id:dmvi:d2e1034" r:label="offices and business settings"/><s:Concept r:about="id:dmvi:d2e1042" r:label="palaces"/><s:Concept r:about="id:dmvi:d2e1059" r:label="prisons"/><s:Concept r:about="id:dmvi:d2e1067" r:label="public houses"/><s:Concept r:about="id:dmvi:d2e1083" r:label="railway stations"/><s:Concept r:about="id:dmvi:d2e1091" r:label="restaurants"/><s:Concept r:about="id:dmvi:d2e1099" r:label="ruins"/><s:Concept r:about="id:dmvi:d2e1107" r:label="schools"/><s:Concept r:about="id:dmvi:d2e1115" r:label="shops"/><s:Concept r:about="id:dmvi:d2e1140" r:label="tents"/><s:Concept r:about="id:dmvi:d2e1148" r:label="theatres"/><s:Concept r:about="id:dmvi:d2e1156" r:label="universities"/><s:Concept r:about="id:dmvi:d2e1164" r:label="windmills"/></s:memberList></s:orderedCollection></s:narrower></s:Concept><s:Concept r:about="id:dmvi:d2e1178" r:label="outdoor sites"><s:narrower><s:orderedCollection><s:memberList r:parseType="Collection"><s:Concept r:about="id:dmvi:d2e1180" r:label="battlefields"/><s:Concept r:about="id:dmvi:d2e1196" r:label="campfires"/><s:Concept r:about="id:dmvi:d2e1204" r:label="campsites"/><s:Concept r:about="id:dmvi:d2e1212" r:label="churchyards"/><s:Concept r:about="id:dmvi:d2e1220" r:label="docks and harbours"/><s:Concept r:about="id:dmvi:d2e1229" r:label="gardens"/><s:Concept r:about="id:dmvi:d2e1245" r:label="mines"/><s:Concept r:about="id:dmvi:d2e1253" r:label="parks and grounds"/></s:memberList></s:orderedCollection></s:narrower></s:Concept><s:Concept r:about="id:dmvi:d2e1259" r:label="architectural features"><s:narrower><s:orderedCollection><s:memberList r:parseType="Collection"><s:Concept r:about="id:dmvi:d2e1261" r:label="archways"/><s:Concept r:about="id:dmvi:d2e1269" r:label="balconies"/><s:Concept r:about="id:dmvi:d2e1293" r:label="fences"/><s:Concept r:about="id:dmvi:d2e1301" r:label="fountains"/><s:Concept r:about="id:dmvi:d2e1309" r:label="gates"/><s:Concept r:about="id:dmvi:d2e1326" r:label="pillars"/><s:Concept r:about="id:dmvi:d2e1334" r:label="porches and verandas"/><s:Concept r:about="id:dmvi:d2e1342" r:label="steps"/><s:Concept r:about="id:dmvi:d2e1358" r:label="tunnels"/><s:Concept r:about="id:dmvi:d2e1366" r:label="walls"/></s:memberList></s:orderedCollection></s:narrower></s:Concept><s:Concept r:about="id:dmvi:d2e1388" r:label="roadways"><s:narrower><s:orderedCollection><s:memberList r:parseType="Collection"><s:Concept r:about="id:dmvi:d2e1390" r:label="roads--streets"/><s:Concept r:about="id:dmvi:d2e1398" r:label="bridges"/><s:Concept r:about="id:dmvi:d2e1423" r:label="paths"/><s:Concept r:about="id:dmvi:d2e1431" r:label="signposts"/></s:memberList></s:orderedCollection></s:narrower></s:Concept><s:Concept r:about="id:dmvi:d2e1437" r:label="rooms"><s:narrower><s:orderedCollection><s:memberList r:parseType="Collection"><s:Concept r:about="id:dmvi:d2e1439" r:label="attics"/><s:Concept r:about="id:dmvi:d2e1455" r:label="bedrooms"/><s:Concept r:about="id:dmvi:d2e1463" r:label="class-rooms"/><s:Concept r:about="id:dmvi:d2e1479" r:label="dining-rooms"/><s:Concept r:about="id:dmvi:d2e1487" r:label="drawing-rooms"/><s:Concept r:about="id:dmvi:d2e1496" r:label="dressing-rooms"/><s:Concept r:about="id:dmvi:d2e1504" r:label="kitchens"/><s:Concept r:about="id:dmvi:d2e1512" r:label="libraries and studies"/><s:Concept r:about="id:dmvi:d2e1520" r:label="nurseries"/><s:Concept r:about="id:dmvi:d2e1528" r:label="sitting-rooms"/></s:memberList></s:orderedCollection></s:narrower></s:Concept><s:Concept r:about="id:dmvi:d2e1534" r:label="features and fittings"><s:narrower><s:orderedCollection><s:memberList r:parseType="Collection"><s:Concept r:about="id:dmvi:d2e1544" r:label="doorways"/><s:Concept r:about="id:dmvi:d2e1552" r:label="fireplaces"/><s:Concept r:about="id:dmvi:d2e1560" r:label="mantelpieces"/><s:Concept r:about="id:dmvi:d2e1568" r:label="stairways"/><s:Concept r:about="id:dmvi:d2e1576" r:label="windows"/></s:memberList></s:orderedCollection></s:narrower></s:Concept><s:Concept r:about="id:dmvi:d2e1607" r:label="vehicle interiors"><s:narrower><s:orderedCollection><s:memberList r:parseType="Collection"><s:Concept r:about="id:dmvi:d2e1617" r:label="ship and boat interiors"/><s:Concept r:about="id:dmvi:d2e1625" r:label="train interiors"/></s:memberList></s:orderedCollection></s:narrower></s:Concept></s:memberList></s:orderedCollection></s:narrower></s:Concept><s:Concept r:about="id:dmvi:d2e1629" r:label="weather and natural disasters"><s:narrower><s:orderedCollection><s:memberList r:parseType="Collection"><s:Concept r:about="id:dmvi:d2e1631" r:label="cold weather"/><s:Concept r:about="id:dmvi:d2e1643" r:label="rain and storms"/><s:Concept r:about="id:dmvi:d2e1655" r:label="snow"/><s:Concept r:about="id:dmvi:d2e1668" r:label="avalanches"/><s:Concept r:about="id:dmvi:d2e1686" r:label="volcanoes"/></s:memberList></s:orderedCollection></s:narrower></s:Concept><s:Concept r:about="id:dmvi:d2e1690" r:label="seasons--times of day"><s:narrower><s:orderedCollection><s:memberList r:parseType="Collection"><s:Concept r:about="id:dmvi:d2e1724" r:label="times of day"><s:narrower><s:orderedCollection><s:memberList r:parseType="Collection"><s:Concept r:about="id:dmvi:d2e1726" r:label="dawn"/><s:Concept r:about="id:dmvi:d2e1734" r:label="evening--night"/></s:memberList></s:orderedCollection></s:narrower></s:Concept></s:memberList></s:orderedCollection></s:narrower></s:Concept></s:memberList></s:orderedCollection></s:narrower></s:Concept><s:Concept r:about="id:dmvi:d2e1737" r:label="people"><s:narrower><s:orderedCollection><s:memberList r:parseType="Collection"><s:Concept r:about="id:dmvi:d2e1739" r:label="figures"><s:narrower><s:orderedCollection><s:memberList r:parseType="Collection"><s:Concept r:about="id:dmvi:d2e1741" r:label="men"/><s:Concept r:about="id:dmvi:d2e1747" r:label="women"/><s:Concept r:about="id:dmvi:d2e1753" r:label="children"/><s:Concept r:about="id:dmvi:d2e1759" r:label="babies"/><s:Concept r:about="id:dmvi:d2e1765" r:label="elderly people"/><s:Concept r:about="id:dmvi:d2e1771" r:label="number of figures"><s:narrower><s:orderedCollection><s:memberList r:parseType="Collection"><s:Concept r:about="id:dmvi:d2e1773" r:label="1 figure"/><s:Concept r:about="id:dmvi:d2e1781" r:label="2 figures"/><s:Concept r:about="id:dmvi:d2e1789" r:label="3 figures"/><s:Concept r:about="id:dmvi:d2e1797" r:label="4 figures"/><s:Concept r:about="id:dmvi:d2e1805" r:label="5 figures"/><s:Concept r:about="id:dmvi:d2e1813" r:label="groups [6-10 figures]"/><s:Concept r:about="id:dmvi:d2e1822" r:label="crowds [10+ figures]"/><s:Concept r:about="id:dmvi:d2e1830" r:label="multiple [in landscape]"/><s:Concept r:about="id:dmvi:d2e1838" r:label="audiences"/><s:Concept r:about="id:dmvi:d2e1846" r:label="romantic couples"/></s:memberList></s:orderedCollection></s:narrower></s:Concept><s:Concept r:about="id:dmvi:d2e1852" r:label="physical characteristics"><s:narrower><s:orderedCollection><s:memberList r:parseType="Collection"><s:Concept r:about="id:dmvi:d2e1854" r:label="baldness"/><s:Concept r:about="id:dmvi:d2e1878" r:label="facial hair"/><s:Concept r:about="id:dmvi:d2e1886" r:label="prostheses"/></s:memberList></s:orderedCollection></s:narrower></s:Concept><s:Concept r:about="id:dmvi:d2e1892" r:label="foreign nationals and ethnic minorities"><s:narrower><s:orderedCollection><s:memberList r:parseType="Collection"><s:Concept r:about="id:dmvi:d2e1894" r:label="African people"/><s:Concept r:about="id:dmvi:d2e1902" r:label="Asian people"/><s:Concept r:about="id:dmvi:d2e1927" r:label="black people"/><s:Concept r:about="id:dmvi:d2e1935" r:label="Dutch people"/><s:Concept r:about="id:dmvi:d2e1991" r:label="Indian people"/><s:Concept r:about="id:dmvi:d2e2000" r:label="indigenous peoples"/><s:Concept r:about="id:dmvi:d2e2008" r:label="Irish people"/><s:Concept r:about="id:dmvi:d2e2032" r:label="Middle-Eastern people"/><s:Concept r:about="id:dmvi:d2e2040" r:label="North American people"/><s:Concept r:about="id:dmvi:d2e2048" r:label="Oriental people"/><s:Concept r:about="id:dmvi:d2e2072" r:label="South American people"/><s:Concept r:about="id:dmvi:d2e2080" r:label="Spanish people"/><s:Concept r:about="id:dmvi:d2e2089" r:label="Swiss people"/></s:memberList></s:orderedCollection></s:narrower></s:Concept><s:Concept r:about="id:dmvi:d2e2095" r:label="mythological figures"><s:narrower><s:orderedCollection><s:memberList r:parseType="Collection"><s:Concept r:about="id:dmvi:d2e2097" r:label="classical heroes"/><s:Concept r:about="id:dmvi:d2e2105" r:label="gods and goddesses"/></s:memberList></s:orderedCollection></s:narrower></s:Concept><s:Concept r:about="id:dmvi:d2e2135" r:label="supernatural figures"><s:narrower><s:orderedCollection><s:memberList r:parseType="Collection"><s:Concept r:about="id:dmvi:d2e2137" r:label="angels"/><s:Concept r:about="id:dmvi:d2e2145" r:label="cherubs"/><s:Concept r:about="id:dmvi:d2e2153" r:label="demons"/><s:Concept r:about="id:dmvi:d2e2161" r:label="devils"/><s:Concept r:about="id:dmvi:d2e2169" r:label="fairies"/><s:Concept r:about="id:dmvi:d2e2178" r:label="Father Christmas"/><s:Concept r:about="id:dmvi:d2e2186" r:label="ghosts"/><s:Concept r:about="id:dmvi:d2e2194" r:label="goblins"/><s:Concept r:about="id:dmvi:d2e2202" r:label="mermaids"/><s:Concept r:about="id:dmvi:d2e2210" r:label="skeletons"/><s:Concept r:about="id:dmvi:d2e2218" r:label="witches and wizards"/></s:memberList></s:orderedCollection></s:narrower></s:Concept></s:memberList></s:orderedCollection></s:narrower></s:Concept><s:Concept r:about="id:dmvi:d2e2222" r:label="relationships"><s:narrower><s:orderedCollection><s:memberList r:parseType="Collection"><s:Concept r:about="id:dmvi:d2e2224" r:label="family relations"><s:narrower><s:orderedCollection><s:memberList r:parseType="Collection"><s:Concept r:about="id:dmvi:d2e2226" r:label="families [general]"/><s:Concept r:about="id:dmvi:d2e2242" r:label="mothers"/><s:Concept r:about="id:dmvi:d2e2258" r:label="siblings"/><s:Concept r:about="id:dmvi:d2e2267" r:label="grandparents"/><s:Concept r:about="id:dmvi:d2e2275" r:label="husbands and wives"/></s:memberList></s:orderedCollection></s:narrower></s:Concept><s:Concept r:about="id:dmvi:d2e2297" r:label="friends and colleagues"><s:narrower><s:orderedCollection><s:memberList r:parseType="Collection"><s:Concept r:about="id:dmvi:d2e2307" r:label="friends"/></s:memberList></s:orderedCollection></s:narrower></s:Concept></s:memberList></s:orderedCollection></s:narrower></s:Concept><s:Concept r:about="id:dmvi:d2e2311" r:label="jobs and roles"><s:narrower><s:orderedCollection><s:memberList r:parseType="Collection"><s:Concept r:about="id:dmvi:d2e2313" r:label="professions"><s:narrower><s:orderedCollection><s:memberList r:parseType="Collection"><s:Concept r:about="id:dmvi:d2e2347" r:label="governesses"/><s:Concept r:about="id:dmvi:d2e2356" r:label="judges"/><s:Concept r:about="id:dmvi:d2e2364" r:label="lawyers"/><s:Concept r:about="id:dmvi:d2e2372" r:label="scientists"/><s:Concept r:about="id:dmvi:d2e2380" r:label="teachers"/></s:memberList></s:orderedCollection></s:narrower></s:Concept><s:Concept r:about="id:dmvi:d2e2386" r:label="vocations"><s:narrower><s:orderedCollection><s:memberList r:parseType="Collection"><s:Concept r:about="id:dmvi:d2e2388" r:label="actors"/><s:Concept r:about="id:dmvi:d2e2396" r:label="artists"/><s:Concept r:about="id:dmvi:d2e2428" r:label="blacksmiths"/><s:Concept r:about="id:dmvi:d2e2436" r:label="butchers"/><s:Concept r:about="id:dmvi:d2e2517" r:label="domestic servants"/><s:Concept r:about="id:dmvi:d2e2525" r:label="jockeys"/><s:Concept r:about="id:dmvi:d2e2534" r:label="labourers"/><s:Concept r:about="id:dmvi:d2e2566" r:label="farm workers"/><s:Concept r:about="id:dmvi:d2e2574" r:label="milkmaids"/><s:Concept r:about="id:dmvi:d2e2582" r:label="miners"/><s:Concept r:about="id:dmvi:d2e2590" r:label="fishermen"/><s:Concept r:about="id:dmvi:d2e2606" r:label="musicians"/><s:Concept r:about="id:dmvi:d2e2614" r:label="hairdressers"/><s:Concept r:about="id:dmvi:d2e2623" r:label="nurses"/><s:Concept r:about="id:dmvi:d2e2647" r:label="policemen"/><s:Concept r:about="id:dmvi:d2e2655" r:label="railway workers"/><s:Concept r:about="id:dmvi:d2e2663" r:label="sailors"/><s:Concept r:about="id:dmvi:d2e2671" r:label="shepherds"/><s:Concept r:about="id:dmvi:d2e2679" r:label="shoemakers"/><s:Concept r:about="id:dmvi:d2e2695" r:label="students"/><s:Concept r:about="id:dmvi:d2e2712" r:label="waiting staff"/></s:memberList></s:orderedCollection></s:narrower></s:Concept><s:Concept r:about="id:dmvi:d2e2734" r:label="religious persons"><s:narrower><s:orderedCollection><s:memberList r:parseType="Collection"><s:Concept r:about="id:dmvi:d2e2736" r:label="bishops"/><s:Concept r:about="id:dmvi:d2e2752" r:label="ministers"/><s:Concept r:about="id:dmvi:d2e2760" r:label="monks"/><s:Concept r:about="id:dmvi:d2e2768" r:label="nuns"/><s:Concept r:about="id:dmvi:d2e2776" r:label="rabbis"/></s:memberList></s:orderedCollection></s:narrower></s:Concept><s:Concept r:about="id:dmvi:d2e2782" r:label="military persons"><s:narrower><s:orderedCollection><s:memberList r:parseType="Collection"><s:Concept r:about="id:dmvi:d2e2784" r:label="gladiators"/><s:Concept r:about="id:dmvi:d2e2792" r:label="knights"/><s:Concept r:about="id:dmvi:d2e2801" r:label="soldiers"/></s:memberList></s:orderedCollection></s:narrower></s:Concept><s:Concept r:about="id:dmvi:d2e2807" r:label="criminals--outsiders"><s:narrower><s:orderedCollection><s:memberList r:parseType="Collection"><s:Concept r:about="id:dmvi:d2e2841" r:label="slaves"/></s:memberList></s:orderedCollection></s:narrower></s:Concept></s:memberList></s:orderedCollection></s:narrower></s:Concept><s:Concept r:about="id:dmvi:d2e2845" r:label="social status"><s:narrower><s:orderedCollection><s:memberList r:parseType="Collection"><s:Concept r:about="id:dmvi:d2e2847" r:label="working classes"/><s:Concept r:about="id:dmvi:d2e2853" r:label="middle classes"/><s:Concept r:about="id:dmvi:d2e2859" r:label="upper classes"><s:narrower><s:orderedCollection><s:memberList r:parseType="Collection"><s:Concept r:about="id:dmvi:d2e2861" r:label="upper classes [general]"/><s:Concept r:about="id:dmvi:d2e2869" r:label="royalty"/><s:Concept r:about="id:dmvi:d2e2877" r:label="aristocracy"/></s:memberList></s:orderedCollection></s:narrower></s:Concept><s:Concept r:about="id:dmvi:d2e2884" r:label="poor"/><s:Concept r:about="id:dmvi:d2e2890" r:label="wealthy"/></s:memberList></s:orderedCollection></s:narrower></s:Concept><s:Concept r:about="id:dmvi:d2e2894" r:label="clothing"><s:narrower><s:orderedCollection><s:memberList r:parseType="Collection"><s:Concept r:about="id:dmvi:d2e2896" r:label="nudes"/><s:Concept r:about="id:dmvi:d2e2902" r:label="Victorian clothing"><s:narrower><s:orderedCollection><s:memberList r:parseType="Collection"><s:Concept r:about="id:dmvi:d2e2904" r:label="men's clothing"/><s:Concept r:about="id:dmvi:d2e2912" r:label="women's clothing"/><s:Concept r:about="id:dmvi:d2e2920" r:label="costumes and fancy dress"/><s:Concept r:about="id:dmvi:d2e2928" r:label="crinoline"/><s:Concept r:about="id:dmvi:d2e2936" r:label="mourning clothing"/><s:Concept r:about="id:dmvi:d2e2944" r:label="school uniforms"/><s:Concept r:about="id:ncse:d9z9999" r:label="children's clothing"/></s:memberList></s:orderedCollection></s:narrower></s:Concept><s:Concept r:about="id:dmvi:d2e2950" r:label="work clothing"><s:narrower><s:orderedCollection><s:memberList r:parseType="Collection"><s:Concept r:about="id:dmvi:d2e2952" r:label="aprons"/><s:Concept r:about="id:dmvi:d2e2969" r:label="uniforms"/></s:memberList></s:orderedCollection></s:narrower></s:Concept><s:Concept r:about="id:dmvi:d2e2975" r:label="sporting clothing"><s:narrower><s:orderedCollection><s:memberList r:parseType="Collection"><s:Concept r:about="id:dmvi:d2e2977" r:label="athletics clothing"/><s:Concept r:about="id:dmvi:d2e3001" r:label="shooting clothing"/></s:memberList></s:orderedCollection></s:narrower></s:Concept><s:Concept r:about="id:dmvi:d2e3007" r:label="wedding clothing"/><s:Concept r:about="id:dmvi:d2e3013" r:label="riding clothing"/><s:Concept r:about="id:dmvi:d2e3019" r:label="eveningwear"/><s:Concept r:about="id:dmvi:d2e3025" r:label="nightwear"/><s:Concept r:about="id:dmvi:d2e3037" r:label="ragged clothing"/><s:Concept r:about="id:dmvi:d2e3044" r:label="regional--climate clothing"><s:narrower><s:orderedCollection><s:memberList r:parseType="Collection"><s:Concept r:about="id:dmvi:d2e3046" r:label="Alpine dress"/><s:Concept r:about="id:dmvi:d2e3062" r:label="Middle Eastern dress"/><s:Concept r:about="id:dmvi:d2e3070" r:label="Native American dress"/><s:Concept r:about="id:dmvi:d2e3078" r:label="Scottish dress"/><s:Concept r:about="id:dmvi:d2e3094" r:label="cold weather clothing"/></s:memberList></s:orderedCollection></s:narrower></s:Concept><s:Concept r:about="id:dmvi:d2e3116" r:label="period clothing"><s:narrower><s:orderedCollection><s:memberList r:parseType="Collection"><s:Concept r:about="id:dmvi:d2e3118" r:label="medieval clothing"/><s:Concept r:about="id:dmvi:d2e3126" r:label="early modern clothing"/><s:Concept r:about="id:dmvi:d2e3135" r:label="seventeenth-century clothing"/><s:Concept r:about="id:dmvi:d2e3143" r:label="eighteenth-century clothing"/><s:Concept r:about="id:dmvi:d2e3151" r:label="Georgian clothing"/><s:Concept r:about="id:dmvi:d2e3159" r:label="armour"/><s:Concept r:about="id:dmvi:d2e3167" r:label="loincloths"/><s:Concept r:about="id:dmvi:d2e3175" r:label="robes"/><s:Concept r:about="id:dmvi:d2e3183" r:label="togas"/></s:memberList></s:orderedCollection></s:narrower></s:Concept><s:Concept r:about="id:dmvi:d2e3189" r:label="accessories"><s:narrower><s:orderedCollection><s:memberList r:parseType="Collection"><s:Concept r:about="id:dmvi:d2e3191" r:label="bags"/><s:Concept r:about="id:dmvi:d2e3199" r:label="blindfolds"/><s:Concept r:about="id:dmvi:d2e3207" r:label="cloaks"/><s:Concept r:about="id:dmvi:d2e3224" r:label="disguises"/><s:Concept r:about="id:dmvi:d2e3232" r:label="eye-glasses"/><s:Concept r:about="id:dmvi:d2e3248" r:label="fans"/><s:Concept r:about="id:dmvi:d2e3256" r:label="feathers"/><s:Concept r:about="id:dmvi:d2e3264" r:label="garlands"/><s:Concept r:about="id:dmvi:d2e3272" r:label="gloves"/><s:Concept r:about="id:dmvi:d2e3288" r:label="hats"/><s:Concept r:about="id:dmvi:d2e3296" r:label="hoods"/><s:Concept r:about="id:dmvi:d2e3304" r:label="jewellery"/><s:Concept r:about="id:dmvi:d2e3313" r:label="masks"/><s:Concept r:about="id:dmvi:d2e3329" r:label="pocket-watches"/><s:Concept r:about="id:dmvi:d2e3345" r:label="ribbons"/><s:Concept r:about="id:dmvi:d2e3369" r:label="scarves"/><s:Concept r:about="id:dmvi:d2e3377" r:label="turbans"/><s:Concept r:about="id:dmvi:d2e3385" r:label="umbrellas"/><s:Concept r:about="id:dmvi:d2e3402" r:label="walking-sticks"/><s:Concept r:about="id:dmvi:d2e3410" r:label="wigs"/></s:memberList></s:orderedCollection></s:narrower></s:Concept></s:memberList></s:orderedCollection></s:narrower></s:Concept></s:memberList></s:orderedCollection></s:narrower></s:Concept><s:Concept r:about="id:dmvi:d2e3412" r:label="activities"><s:narrower><s:orderedCollection><s:memberList r:parseType="Collection"><s:Concept r:about="id:dmvi:d2e3414" r:label="physical positions"><s:narrower><s:orderedCollection><s:memberList r:parseType="Collection"><s:Concept r:about="id:dmvi:d2e3416" r:label="postures"><s:narrower><s:orderedCollection><s:memberList r:parseType="Collection"><s:Concept r:about="id:dmvi:d2e3418" r:label="kneeling"/><s:Concept r:about="id:dmvi:d2e3426" r:label="leaning"/><s:Concept r:about="id:dmvi:d2e3434" r:label="lying down"/><s:Concept r:about="id:dmvi:d2e3442" r:label="sitting"/></s:memberList></s:orderedCollection></s:narrower></s:Concept><s:Concept r:about="id:dmvi:d2e3448" r:label="hand positions"><s:narrower><s:orderedCollection><s:memberList r:parseType="Collection"><s:Concept r:about="id:dmvi:d2e3450" r:label="clasping hands"/><s:Concept r:about="id:dmvi:d2e3458" r:label="holding hands"/><s:Concept r:about="id:dmvi:d2e3466" r:label="pointing"/><s:Concept r:about="id:dmvi:d2e3474" r:label="shaking hands"/></s:memberList></s:orderedCollection></s:narrower></s:Concept></s:memberList></s:orderedCollection></s:narrower></s:Concept><s:Concept r:about="id:dmvi:d2e3478" r:label="actions and speech"><s:narrower><s:orderedCollection><s:memberList r:parseType="Collection"><s:Concept r:about="id:dmvi:d2e3480" r:label="physical motions"><s:narrower><s:orderedCollection><s:memberList r:parseType="Collection"><s:Concept r:about="id:dmvi:d2e3482" r:label="acrobatics"/><s:Concept r:about="id:dmvi:d2e3499" r:label="carrying"/><s:Concept r:about="id:dmvi:d2e3507" r:label="catching"/><s:Concept r:about="id:dmvi:d2e3523" r:label="climbing"/><s:Concept r:about="id:dmvi:d2e3531" r:label="dancing"/><s:Concept r:about="id:dmvi:d2e3555" r:label="drinking"/><s:Concept r:about="id:dmvi:d2e3563" r:label="eating"/><s:Concept r:about="id:dmvi:d2e3580" r:label="falling"/><s:Concept r:about="id:dmvi:d2e3612" r:label="jumping"/><s:Concept r:about="id:dmvi:d2e3620" r:label="leading"/><s:Concept r:about="id:dmvi:d2e3628" r:label="meeting"/><s:Concept r:about="id:dmvi:d2e3644" r:label="playing"/><s:Concept r:about="id:dmvi:d2e3652" r:label="pushing--pulling"/><s:Concept r:about="id:dmvi:d2e3669" r:label="running"/><s:Concept r:about="id:dmvi:d2e3685" r:label="smoking"/><s:Concept r:about="id:dmvi:d2e3709" r:label="spying"/><s:Concept r:about="id:dmvi:d2e3717" r:label="swimming"/><s:Concept r:about="id:dmvi:d2e3725" r:label="throwing"/><s:Concept r:about="id:dmvi:d2e3741" r:label="walking"/><s:Concept r:about="id:dmvi:d2e3749" r:label="watching"/></s:memberList></s:orderedCollection></s:narrower></s:Concept><s:Concept r:about="id:dmvi:d2e3764" r:label="verbal communications"><s:narrower><s:orderedCollection><s:memberList r:parseType="Collection"><s:Concept r:about="id:dmvi:d2e3774" r:label="acting"/><s:Concept r:about="id:dmvi:d2e3798" r:label="asking"/><s:Concept r:about="id:dmvi:d2e3806" r:label="begging"/><s:Concept r:about="id:dmvi:d2e3822" r:label="crying"/><s:Concept r:about="id:dmvi:d2e3847" r:label="praying"/><s:Concept r:about="id:dmvi:d2e3871" r:label="shouting"/><s:Concept r:about="id:dmvi:d2e3879" r:label="singing"/><s:Concept r:about="id:dmvi:d2e3887" r:label="talking"/></s:memberList></s:orderedCollection></s:narrower></s:Concept><s:Concept r:about="id:dmvi:d2e3925" r:label="manual and farm work"><s:narrower><s:orderedCollection><s:memberList r:parseType="Collection"><s:Concept r:about="id:dmvi:d2e3952" r:label="cutting and chopping"/><s:Concept r:about="id:dmvi:d2e3960" r:label="cleaning"/><s:Concept r:about="id:dmvi:d2e3968" r:label="cooking and preparing"/><s:Concept r:about="id:dmvi:d2e3976" r:label="digging"/><s:Concept r:about="id:dmvi:d2e3984" r:label="gardening"/><s:Concept r:about="id:dmvi:d2e3992" r:label="herding"/><s:Concept r:about="id:dmvi:d2e4033" r:label="picking"/><s:Concept r:about="id:dmvi:d2e4049" r:label="reaping"/><s:Concept r:about="id:dmvi:d2e4065" r:label="sewing and knitting"/><s:Concept r:about="id:dmvi:d2e4089" r:label="weaving"/></s:memberList></s:orderedCollection></s:narrower></s:Concept><s:Concept r:about="id:dmvi:d2e4095" r:label="fighting, hunting and military actions"><s:narrower><s:orderedCollection><s:memberList r:parseType="Collection"><s:Concept r:about="id:dmvi:d2e4097" r:label="duelling"/><s:Concept r:about="id:dmvi:d2e4105" r:label="escaping"/><s:Concept r:about="id:dmvi:d2e4114" r:label="fighting"/><s:Concept r:about="id:dmvi:d2e4122" r:label="fishing"/><s:Concept r:about="id:dmvi:d2e4138" r:label="hunting and trapping"/><s:Concept r:about="id:dmvi:d2e4146" r:label="killing"/><s:Concept r:about="id:dmvi:d2e4154" r:label="marching"/><s:Concept r:about="id:dmvi:d2e4170" r:label="shooting"/></s:memberList></s:orderedCollection></s:narrower></s:Concept><s:Concept r:about="id:dmvi:d2e4176" r:label="transactions"><s:narrower><s:orderedCollection><s:memberList r:parseType="Collection"><s:Concept r:about="id:dmvi:d2e4178" r:label="buying and selling"/><s:Concept r:about="id:dmvi:d2e4186" r:label="loaning"/><s:Concept r:about="id:dmvi:d2e4194" r:label="gambling"/></s:memberList></s:orderedCollection></s:narrower></s:Concept><s:Concept r:about="id:dmvi:d2e4201" r:label="affectionate actions"><s:narrower><s:orderedCollection><s:memberList r:parseType="Collection"><s:Concept r:about="id:dmvi:d2e4211" r:label="comforting"/><s:Concept r:about="id:dmvi:d2e4219" r:label="courtship"/><s:Concept r:about="id:dmvi:d2e4227" r:label="embracing"/><s:Concept r:about="id:dmvi:d2e4235" r:label="helping"/><s:Concept r:about="id:dmvi:d2e4243" r:label="kissing"/><s:Concept r:about="id:dmvi:d2e4251" r:label="nursing"/><s:Concept r:about="id:dmvi:d2e4267" r:label="stroking"/><s:Concept r:about="id:dmvi:d2e4275" r:label="welcoming"/></s:memberList></s:orderedCollection></s:narrower></s:Concept><s:Concept r:about="id:dmvi:d2e4281" r:label="mental and creative activities"><s:narrower><s:orderedCollection><s:memberList r:parseType="Collection"><s:Concept r:about="id:dmvi:d2e4292" r:label="listening"/><s:Concept r:about="id:dmvi:d2e4300" r:label="painting and drawing"/><s:Concept r:about="id:dmvi:d2e4308" r:label="reading"/><s:Concept r:about="id:dmvi:d2e4316" r:label="relaxing"/><s:Concept r:about="id:dmvi:d2e4332" r:label="teaching"/><s:Concept r:about="id:dmvi:d2e4340" r:label="thinking"/><s:Concept r:about="id:dmvi:d2e4348" r:label="writing"/></s:memberList></s:orderedCollection></s:narrower></s:Concept><s:Concept r:about="id:dmvi:d2e4354" r:label="vehicular motions"><s:narrower><s:orderedCollection><s:memberList r:parseType="Collection"><s:Concept r:about="id:dmvi:d2e4364" r:label="driving"/><s:Concept r:about="id:dmvi:d2e4372" r:label="horse-riding"/><s:Concept r:about="id:dmvi:d2e4381" r:label="rowing and punting"/><s:Concept r:about="id:dmvi:d2e4389" r:label="sailing"/></s:memberList></s:orderedCollection></s:narrower></s:Concept></s:memberList></s:orderedCollection></s:narrower></s:Concept><s:Concept r:about="id:dmvi:d2e4393" r:label="emotions and states"><s:narrower><s:orderedCollection><s:memberList r:parseType="Collection"><s:Concept r:about="id:dmvi:d2e4395" r:label="emotions"><s:narrower><s:orderedCollection><s:memberList r:parseType="Collection"><s:Concept r:about="id:dmvi:d2e4405" r:label="distress"/><s:Concept r:about="id:dmvi:d2e4413" r:label="fear"/><s:Concept r:about="id:dmvi:d2e4437" r:label="happiness"/><s:Concept r:about="id:dmvi:d2e4445" r:label="hatred"/><s:Concept r:about="id:dmvi:d2e4470" r:label="love"/><s:Concept r:about="id:dmvi:d2e4486" r:label="sadness"/><s:Concept r:about="id:dmvi:d2e4494" r:label="surprise"/></s:memberList></s:orderedCollection></s:narrower></s:Concept><s:Concept r:about="id:dmvi:d2e4500" r:label="characteristics"><s:narrower><s:orderedCollection><s:memberList r:parseType="Collection"><s:Concept r:about="id:dmvi:d2e4534" r:label="greed"/></s:memberList></s:orderedCollection></s:narrower></s:Concept><s:Concept r:about="id:dmvi:d2e4573" r:label="physical states"><s:narrower><s:orderedCollection><s:memberList r:parseType="Collection"><s:Concept r:about="id:dmvi:d2e4599" r:label="ill--injured"/><s:Concept r:about="id:dmvi:d2e4607" r:label="in pain"/><s:Concept r:about="id:dmvi:d2e4615" r:label="sleeping"/><s:Concept r:about="id:dmvi:d2e4631" r:label="tiredness"/><s:Concept r:about="id:dmvi:d2e4639" r:label="unconsciousness"/></s:memberList></s:orderedCollection></s:narrower></s:Concept></s:memberList></s:orderedCollection></s:narrower></s:Concept></s:memberList></s:orderedCollection></s:narrower></s:Concept><s:Concept r:about="id:dmvi:d2e4642" r:label="objects"><s:narrower><s:orderedCollection><s:memberList r:parseType="Collection"><s:Concept r:about="id:dmvi:d2e4644" r:label="tools and implements"><s:narrower><s:orderedCollection><s:memberList r:parseType="Collection"><s:Concept r:about="id:dmvi:d2e4646" r:label="domestic objects"><s:narrower><s:orderedCollection><s:memberList r:parseType="Collection"><s:Concept r:about="id:dmvi:d2e4648" r:label="basins"/><s:Concept r:about="id:dmvi:d2e4656" r:label="baskets"/><s:Concept r:about="id:dmvi:d2e4672" r:label="bottles"/><s:Concept r:about="id:dmvi:d2e4680" r:label="buckets"/><s:Concept r:about="id:dmvi:d2e4688" r:label="cleaning equipment"/><s:Concept r:about="id:dmvi:d2e4696" r:label="clocks"/><s:Concept r:about="id:dmvi:d2e4728" r:label="crockery and pottery"/><s:Concept r:about="id:dmvi:d2e4737" r:label="cups"/><s:Concept r:about="id:dmvi:d2e4745" r:label="cutlery"/><s:Concept r:about="id:dmvi:d2e4761" r:label="fabrics"/><s:Concept r:about="id:dmvi:d2e4817" r:label="jugs"/><s:Concept r:about="id:dmvi:d2e4834" r:label="keys"/><s:Concept r:about="id:dmvi:d2e4850" r:label="ornaments"/><s:Concept r:about="id:dmvi:d2e4874" r:label="scissors"/><s:Concept r:about="id:dmvi:d2e4898" r:label="vases"/><s:Concept r:about="id:dmvi:d2e4915" r:label="watering-cans"/><s:Concept r:about="id:dmvi:d2e4923" r:label="weights and scales"/></s:memberList></s:orderedCollection></s:narrower></s:Concept><s:Concept r:about="id:dmvi:d2e4929" r:label="lighting devices"><s:narrower><s:orderedCollection><s:memberList r:parseType="Collection"><s:Concept r:about="id:dmvi:d2e4931" r:label="candles and candlesticks"/><s:Concept r:about="id:dmvi:d2e4947" r:label="lamps"/><s:Concept r:about="id:dmvi:d2e4955" r:label="torches"/></s:memberList></s:orderedCollection></s:narrower></s:Concept><s:Concept r:about="id:dmvi:d2e4961" r:label="farming equipment"><s:narrower><s:orderedCollection><s:memberList r:parseType="Collection"><s:Concept r:about="id:dmvi:d2e5004" r:label="scythes and sickles"/></s:memberList></s:orderedCollection></s:narrower></s:Concept><s:Concept r:about="id:dmvi:d2e5018" r:label="labouring equipment"><s:narrower><s:orderedCollection><s:memberList r:parseType="Collection"><s:Concept r:about="id:dmvi:d2e5020" r:label="axes"/><s:Concept r:about="id:dmvi:d2e5028" r:label="barrels"/><s:Concept r:about="id:dmvi:d2e5044" r:label="builder's tools"/><s:Concept r:about="id:dmvi:d2e5068" r:label="ladders"/><s:Concept r:about="id:dmvi:d2e5093" r:label="ropes"/><s:Concept r:about="id:dmvi:d2e5101" r:label="spades"/></s:memberList></s:orderedCollection></s:narrower></s:Concept><s:Concept r:about="id:dmvi:d2e5115" r:label="creative implements"><s:narrower><s:orderedCollection><s:memberList r:parseType="Collection"><s:Concept r:about="id:dmvi:d2e5117" r:label="artist's equipment"/><s:Concept r:about="id:dmvi:d2e5133" r:label="weaving equipment"/><s:Concept r:about="id:dmvi:d2e5141" r:label="writing equipment"/></s:memberList></s:orderedCollection></s:narrower></s:Concept><s:Concept r:about="id:dmvi:d2e5147" r:label="medical equipment"><s:narrower><s:orderedCollection><s:memberList r:parseType="Collection"><s:Concept r:about="id:dmvi:d2e5149" r:label="bandages"/></s:memberList></s:orderedCollection></s:narrower></s:Concept><s:Concept r:about="id:dmvi:d2e5163" r:label="scientific objects"><s:narrower><s:orderedCollection><s:memberList r:parseType="Collection"><s:Concept r:about="id:dmvi:d2e5182" r:label="globes"/><s:Concept r:about="id:dmvi:d2e5190" r:label="laboratory equipment"/><s:Concept r:about="id:dmvi:d2e5206" r:label="telescopes"/></s:memberList></s:orderedCollection></s:narrower></s:Concept><s:Concept r:about="id:dmvi:d2e5212" r:label="weapons"><s:narrower><s:orderedCollection><s:memberList r:parseType="Collection"><s:Concept r:about="id:dmvi:d2e5214" r:label="battleaxes"/><s:Concept r:about="id:dmvi:d2e5222" r:label="bows and arrows"/><s:Concept r:about="id:dmvi:d2e5230" r:label="cannons"/><s:Concept r:about="id:dmvi:d2e5238" r:label="chains"/><s:Concept r:about="id:dmvi:d2e5254" r:label="guns"/><s:Concept r:about="id:dmvi:d2e5262" r:label="knives"/><s:Concept r:about="id:dmvi:d2e5271" r:label="shields"/><s:Concept r:about="id:dmvi:d2e5279" r:label="spears"/><s:Concept r:about="id:dmvi:d2e5287" r:label="stones and rocks"/><s:Concept r:about="id:dmvi:d2e5295" r:label="swords"/><s:Concept r:about="id:dmvi:d2e5303" r:label="tridents"/></s:memberList></s:orderedCollection></s:narrower></s:Concept></s:memberList></s:orderedCollection></s:narrower></s:Concept><s:Concept r:about="id:dmvi:d2e5307" r:label="furnishings"><s:narrower><s:orderedCollection><s:memberList r:parseType="Collection"><s:Concept r:about="id:dmvi:d2e5309" r:label="armchairs"/><s:Concept r:about="id:dmvi:d2e5315" r:label="beds"/><s:Concept r:about="id:dmvi:d2e5333" r:label="bookcases"/><s:Concept r:about="id:dmvi:d2e5339" r:label="boxes"/><s:Concept r:about="id:dmvi:d2e5346" r:label="carpets"/><s:Concept r:about="id:dmvi:d2e5352" r:label="chairs"/><s:Concept r:about="id:dmvi:d2e5364" r:label="cradles"/><s:Concept r:about="id:dmvi:d2e5370" r:label="cupboards"/><s:Concept r:about="id:dmvi:d2e5376" r:label="curtains"/><s:Concept r:about="id:dmvi:d2e5382" r:label="decorations"/><s:Concept r:about="id:dmvi:d2e5388" r:label="desks"/><s:Concept r:about="id:dmvi:d2e5394" r:label="dressing-tables"/><s:Concept r:about="id:dmvi:d2e5406" r:label="lecterns"/><s:Concept r:about="id:dmvi:d2e5413" r:label="mirrors"/><s:Concept r:about="id:dmvi:d2e5419" r:label="panelling"/><s:Concept r:about="id:dmvi:d2e5431" r:label="screens"/><s:Concept r:about="id:dmvi:d2e5437" r:label="shelves"/><s:Concept r:about="id:dmvi:d2e5455" r:label="tables"/></s:memberList></s:orderedCollection></s:narrower></s:Concept><s:Concept r:about="id:dmvi:d2e5478" r:label="recreational objects"><s:narrower><s:orderedCollection><s:memberList r:parseType="Collection"><s:Concept r:about="id:dmvi:d2e5480" r:label="sporting objects"><s:narrower><s:orderedCollection><s:memberList r:parseType="Collection"><s:Concept r:about="id:dmvi:d2e5482" r:label="balls"/><s:Concept r:about="id:dmvi:d2e5530" r:label="fishing equipment"/><s:Concept r:about="id:dmvi:d2e5538" r:label="playing cards"/></s:memberList></s:orderedCollection></s:narrower></s:Concept><s:Concept r:about="id:dmvi:d2e5544" r:label="toys"><s:narrower><s:orderedCollection><s:memberList r:parseType="Collection"><s:Concept r:about="id:dmvi:d2e5554" r:label="dolls"/></s:memberList></s:orderedCollection></s:narrower></s:Concept></s:memberList></s:orderedCollection></s:narrower></s:Concept><s:Concept r:about="id:dmvi:d2e5599" r:label="transport and travel"><s:narrower><s:orderedCollection><s:memberList r:parseType="Collection"><s:Concept r:about="id:dmvi:d2e5601" r:label="vehicles"><s:narrower><s:orderedCollection><s:memberList r:parseType="Collection"><s:Concept r:about="id:dmvi:d2e5603" r:label="ships"/><s:Concept r:about="id:dmvi:d2e5611" r:label="boats"/><s:Concept r:about="id:dmvi:d2e5627" r:label="sailing and boating equipment"/><s:Concept r:about="id:dmvi:d2e5635" r:label="carriages"/><s:Concept r:about="id:dmvi:d2e5643" r:label="carts"/><s:Concept r:about="id:dmvi:d2e5651" r:label="omnibuses"/><s:Concept r:about="id:dmvi:d2e5660" r:label="trains"/><s:Concept r:about="id:dmvi:d2e5668" r:label="sleighs and sleds"/></s:memberList></s:orderedCollection></s:narrower></s:Concept><s:Concept r:about="id:dmvi:d2e5690" r:label="travel items"><s:narrower><s:orderedCollection><s:memberList r:parseType="Collection"><s:Concept r:about="id:dmvi:d2e5692" r:label="horse-whips"/><s:Concept r:about="id:dmvi:d2e5700" r:label="luggage"/><s:Concept r:about="id:dmvi:d2e5708" r:label="maps"/><s:Concept r:about="id:dmvi:d2e5716" r:label="riding equipment"/></s:memberList></s:orderedCollection></s:narrower></s:Concept></s:memberList></s:orderedCollection></s:narrower></s:Concept><s:Concept r:about="id:dmvi:d2e5720" r:label="cultural objects"><s:narrower><s:orderedCollection><s:memberList r:parseType="Collection"><s:Concept r:about="id:dmvi:d2e5722" r:label="written word"><s:narrower><s:orderedCollection><s:memberList r:parseType="Collection"><s:Concept r:about="id:dmvi:d2e5732" r:label="architectural plans"/><s:Concept r:about="id:dmvi:d2e5740" r:label="books"/><s:Concept r:about="id:dmvi:d2e5749" r:label="calling cards"/><s:Concept r:about="id:dmvi:d2e5765" r:label="letters"/><s:Concept r:about="id:dmvi:d2e5773" r:label="manuscripts"/><s:Concept r:about="id:dmvi:d2e5789" r:label="periodicals"/><s:Concept r:about="id:dmvi:d2e5797" r:label="scripts"/><s:Concept r:about="id:dmvi:d2e5805" r:label="signs and posters"/><s:Concept r:about="id:dmvi:d2e5813" r:label="songsheets"/></s:memberList></s:orderedCollection></s:narrower></s:Concept><s:Concept r:about="id:dmvi:d2e5860" r:label="visual arts"><s:narrower><s:orderedCollection><s:memberList r:parseType="Collection"><s:Concept r:about="id:dmvi:d2e5862" r:label="embroidery"/><s:Concept r:about="id:dmvi:d2e5870" r:label="paintings"/><s:Concept r:about="id:dmvi:d2e5878" r:label="sculpture"/><s:Concept r:about="id:dmvi:d2e5886" r:label="sketch-books"/></s:memberList></s:orderedCollection></s:narrower></s:Concept><s:Concept r:about="id:dmvi:d2e5892" r:label="musical objects"><s:narrower><s:orderedCollection><s:memberList r:parseType="Collection"><s:Concept r:about="id:dmvi:d2e5902" r:label="brass instruments"/><s:Concept r:about="id:dmvi:d2e5910" r:label="drums"/><s:Concept r:about="id:dmvi:d2e5927" r:label="harps"/><s:Concept r:about="id:dmvi:d2e5935" r:label="pianos and organs"/><s:Concept r:about="id:dmvi:d2e5951" r:label="sheet music"/><s:Concept r:about="id:dmvi:d2e5959" r:label="violins"/></s:memberList></s:orderedCollection></s:narrower></s:Concept><s:Concept r:about="id:dmvi:d2e5973" r:label="religious objects"><s:narrower><s:orderedCollection><s:memberList r:parseType="Collection"><s:Concept r:about="id:dmvi:d2e5975" r:label="altars"/><s:Concept r:about="id:dmvi:d2e5983" r:label="Bibles"/><s:Concept r:about="id:dmvi:d2e5991" r:label="coffins and biers"/><s:Concept r:about="id:dmvi:d2e5999" r:label="crucifixes"/><s:Concept r:about="id:dmvi:d2e6007" r:label="graves and gravestones"/><s:Concept r:about="id:dmvi:d2e6016" r:label="prayer books"/><s:Concept r:about="id:dmvi:d2e6040" r:label="statues of Jesus"/></s:memberList></s:orderedCollection></s:narrower></s:Concept><s:Concept r:about="id:dmvi:d2e6046" r:label="status objects"><s:narrower><s:orderedCollection><s:memberList r:parseType="Collection"><s:Concept r:about="id:dmvi:d2e6048" r:label="crests"/><s:Concept r:about="id:dmvi:d2e6056" r:label="crowns"/><s:Concept r:about="id:dmvi:d2e6064" r:label="flags"/><s:Concept r:about="id:dmvi:d2e6072" r:label="regalia"/><s:Concept r:about="id:dmvi:d2e6080" r:label="thrones"/></s:memberList></s:orderedCollection></s:narrower></s:Concept><s:Concept r:about="id:dmvi:d2e6086" r:label="valuable objects"><s:narrower><s:orderedCollection><s:memberList r:parseType="Collection"><s:Concept r:about="id:dmvi:d2e6096" r:label="gold and silver"/><s:Concept r:about="id:dmvi:d2e6105" r:label="jewels"/><s:Concept r:about="id:dmvi:d2e6113" r:label="medals"/><s:Concept r:about="id:dmvi:d2e6129" r:label="money"/></s:memberList></s:orderedCollection></s:narrower></s:Concept></s:memberList></s:orderedCollection></s:narrower></s:Concept><s:Concept r:about="id:dmvi:d2e6149" r:label="food and drink"><s:narrower><s:orderedCollection><s:memberList r:parseType="Collection"><s:Concept r:about="id:dmvi:d2e6151" r:label="food"><s:narrower><s:orderedCollection><s:memberList r:parseType="Collection"><s:Concept r:about="id:dmvi:d2e6153" r:label="food [general]"/><s:Concept r:about="id:dmvi:d2e6169" r:label="condiments"/><s:Concept r:about="id:dmvi:d2e6185" r:label="eggs"/><s:Concept r:about="id:dmvi:d2e6194" r:label="fruit"/><s:Concept r:about="id:dmvi:d2e6202" r:label="meat and fish"/><s:Concept r:about="id:dmvi:d2e6218" r:label="vegetables"/></s:memberList></s:orderedCollection></s:narrower></s:Concept><s:Concept r:about="id:dmvi:d2e6224" r:label="drink"><s:narrower><s:orderedCollection><s:memberList r:parseType="Collection"><s:Concept r:about="id:dmvi:d2e6226" r:label="drink [general]"/><s:Concept r:about="id:dmvi:d2e6274" r:label="spirits"/><s:Concept r:about="id:dmvi:d2e6283" r:label="tea and coffee"/><s:Concept r:about="id:dmvi:d2e6291" r:label="wine"/></s:memberList></s:orderedCollection></s:narrower></s:Concept><s:Concept r:about="id:dmvi:d2e6297" r:label="other ingestibles"><s:narrower><s:orderedCollection><s:memberList r:parseType="Collection"><s:Concept r:about="id:dmvi:d2e6307" r:label="medicines"/><s:Concept r:about="id:dmvi:d2e6323" r:label="tobacco"/></s:memberList></s:orderedCollection></s:narrower></s:Concept></s:memberList></s:orderedCollection></s:narrower></s:Concept><s:Concept r:about="id:dmvi:d2e6327" r:label="human biology"><s:narrower><s:orderedCollection><s:memberList r:parseType="Collection"><s:Concept r:about="id:dmvi:d2e6329" r:label="blood"/><s:Concept r:about="id:dmvi:d2e6335" r:label="corpses"/><s:Concept r:about="id:dmvi:d2e6347" r:label="hair"/><s:Concept r:about="id:dmvi:d2e6353" r:label="human skeletons"/></s:memberList></s:orderedCollection></s:narrower></s:Concept><s:Concept r:about="id:dmvi:d2e6364" r:label="birds and animals"><s:narrower><s:orderedCollection><s:memberList r:parseType="Collection"><s:Concept r:about="id:dmvi:d2e6366" r:label="animals"><s:narrower><s:orderedCollection><s:memberList r:parseType="Collection"><s:Concept r:about="id:dmvi:d2e6368" r:label="apes"/><s:Concept r:about="id:dmvi:d2e6376" r:label="bats"/><s:Concept r:about="id:dmvi:d2e6384" r:label="bears"/><s:Concept r:about="id:dmvi:d2e6392" r:label="camels"/><s:Concept r:about="id:dmvi:d2e6400" r:label="cats"/><s:Concept r:about="id:dmvi:d2e6408" r:label="cows"/><s:Concept r:about="id:dmvi:d2e6416" r:label="deer"/><s:Concept r:about="id:dmvi:d2e6424" r:label="dogs"/><s:Concept r:about="id:dmvi:d2e6432" r:label="donkeys"/><s:Concept r:about="id:dmvi:d2e6440" r:label="elephants"/><s:Concept r:about="id:dmvi:d2e6449" r:label="foxes"/><s:Concept r:about="id:dmvi:d2e6465" r:label="hares and rabbits"/><s:Concept r:about="id:dmvi:d2e6473" r:label="horses"/><s:Concept r:about="id:dmvi:d2e6481" r:label="jackals"/><s:Concept r:about="id:dmvi:d2e6489" r:label="lions"/><s:Concept r:about="id:dmvi:d2e6497" r:label="lizards"/><s:Concept r:about="id:dmvi:d2e6505" r:label="pigs"/><s:Concept r:about="id:dmvi:d2e6513" r:label="rodents"/><s:Concept r:about="id:dmvi:d2e6521" r:label="sheep"/><s:Concept r:about="id:dmvi:d2e6529" r:label="snakes"/><s:Concept r:about="id:dmvi:d2e6538" r:label="tigers"/><s:Concept r:about="id:dmvi:d2e6546" r:label="toads and frogs"/><s:Concept r:about="id:dmvi:d2e6562" r:label="wolves"/></s:memberList></s:orderedCollection></s:narrower></s:Concept><s:Concept r:about="id:dmvi:d2e6568" r:label="birds"><s:narrower><s:orderedCollection><s:memberList r:parseType="Collection"><s:Concept r:about="id:dmvi:d2e6570" r:label="birds [general]"/><s:Concept r:about="id:dmvi:d2e6586" r:label="birds of prey"/><s:Concept r:about="id:dmvi:d2e6602" r:label="chickens"/><s:Concept r:about="id:dmvi:d2e6643" r:label="ducks"/><s:Concept r:about="id:dmvi:d2e6659" r:label="geese"/><s:Concept r:about="id:dmvi:d2e6667" r:label="gulls"/><s:Concept r:about="id:dmvi:d2e6699" r:label="owls"/><s:Concept r:about="id:dmvi:d2e6740" r:label="ravens"/><s:Concept r:about="id:dmvi:d2e6764" r:label="swallows"/><s:Concept r:about="id:dmvi:d2e6772" r:label="swans"/></s:memberList></s:orderedCollection></s:narrower></s:Concept><s:Concept r:about="id:dmvi:d2e6786" r:label="fish"/><s:Concept r:about="id:dmvi:d2e6792" r:label="insects"/><s:Concept r:about="id:dmvi:d2e6799" r:label="mythological creatures"><s:narrower><s:orderedCollection><s:memberList r:parseType="Collection"><s:Concept r:about="id:dmvi:d2e6801" r:label="dragons"/><s:Concept r:about="id:dmvi:d2e6809" r:label="Pegasus"/></s:memberList></s:orderedCollection></s:narrower></s:Concept><s:Concept r:about="id:dmvi:d2e6823" r:label="animal-related objects"><s:narrower><s:orderedCollection><s:memberList r:parseType="Collection"><s:Concept r:about="id:dmvi:d2e6833" r:label="animal skins"/><s:Concept r:about="id:dmvi:d2e6841" r:label="birds' feathers"/><s:Concept r:about="id:dmvi:d2e6865" r:label="nests and eggs"/><s:Concept r:about="id:dmvi:d2e6873" r:label="seashells"/></s:memberList></s:orderedCollection></s:narrower></s:Concept></s:memberList></s:orderedCollection></s:narrower></s:Concept><s:Concept r:about="id:dmvi:d2e6877" r:label="vegetation"><s:narrower><s:orderedCollection><s:memberList r:parseType="Collection"><s:Concept r:about="id:dmvi:d2e6879" r:label="trees"><s:narrower><s:orderedCollection><s:memberList r:parseType="Collection"><s:Concept r:about="id:dmvi:d2e6881" r:label="trees [general]"/><s:Concept r:about="id:dmvi:d2e6898" r:label="beeches"/><s:Concept r:about="id:dmvi:d2e6906" r:label="oaks"/><s:Concept r:about="id:dmvi:d2e6914" r:label="palms"/><s:Concept r:about="id:dmvi:d2e6922" r:label="timber"/></s:memberList></s:orderedCollection></s:narrower></s:Concept><s:Concept r:about="id:dmvi:d2e6936" r:label="plants"><s:narrower><s:orderedCollection><s:memberList r:parseType="Collection"><s:Concept r:about="id:dmvi:d2e6938" r:label="plants [general]"/><s:Concept r:about="id:dmvi:d2e6946" r:label="bushes"/><s:Concept r:about="id:dmvi:d2e6954" r:label="ferns"/><s:Concept r:about="id:dmvi:d2e6962" r:label="holly"/><s:Concept r:about="id:dmvi:d2e6970" r:label="mistletoe"/><s:Concept r:about="id:dmvi:d2e6979" r:label="reeds"/></s:memberList></s:orderedCollection></s:narrower></s:Concept><s:Concept r:about="id:dmvi:d2e6993" r:label="crops"><s:narrower><s:orderedCollection><s:memberList r:parseType="Collection"><s:Concept r:about="id:dmvi:d2e6995" r:label="cereals"/></s:memberList></s:orderedCollection></s:narrower></s:Concept><s:Concept r:about="id:dmvi:d2e7009" r:label="flowers"><s:narrower><s:orderedCollection><s:memberList r:parseType="Collection"><s:Concept r:about="id:dmvi:d2e7011" r:label="flowers [general]"/><s:Concept r:about="id:dmvi:d2e7019" r:label="bouquets"/><s:Concept r:about="id:dmvi:d2e7043" r:label="roses"/></s:memberList></s:orderedCollection></s:narrower></s:Concept></s:memberList></s:orderedCollection></s:narrower></s:Concept></s:memberList></s:orderedCollection></s:narrower></s:Concept><s:Concept r:about="id:dmvi:d2e7045" r:label="themes"><s:narrower><s:orderedCollection><s:memberList r:parseType="Collection"><s:Concept r:about="id:dmvi:d2e7047" r:label="society and culture"><s:narrower><s:orderedCollection><s:memberList r:parseType="Collection"><s:Concept r:about="id:dmvi:d2e7049" r:label="politics"><s:narrower><s:orderedCollection><s:memberList r:parseType="Collection"><s:Concept r:about="id:dmvi:d2e7059" r:label="governments"/></s:memberList></s:orderedCollection></s:narrower></s:Concept><s:Concept r:about="id:dmvi:d2e7227" r:label="leisure and recreation"><s:narrower><s:orderedCollection><s:memberList r:parseType="Collection"><s:Concept r:about="id:dmvi:d2e7286" r:label="parties"/><s:Concept r:about="id:dmvi:d2e7310" r:label="theatre"/></s:memberList></s:orderedCollection></s:narrower></s:Concept><s:Concept r:about="id:dmvi:d2e7381" r:label="arts and sciences"><s:narrower><s:orderedCollection><s:memberList r:parseType="Collection"><s:Concept r:about="id:dmvi:d2e7407" r:label="medical science"/><s:Concept r:about="id:dmvi:d2e7415" r:label="natural science"/><s:Concept r:about="id:dmvi:d2e7424" r:label="astrology"/></s:memberList></s:orderedCollection></s:narrower></s:Concept></s:memberList></s:orderedCollection></s:narrower></s:Concept><s:Concept r:about="id:dmvi:d2e7452" r:label="travel and tourism"><s:narrower><s:orderedCollection><s:memberList r:parseType="Collection"><s:Concept r:about="id:dmvi:d2e7454" r:label="exploration"/><s:Concept r:about="id:dmvi:d2e7466" r:label="journeys"/></s:memberList></s:orderedCollection></s:narrower></s:Concept><s:Concept r:about="id:dmvi:d2e7476" r:label="religion"><s:narrower><s:orderedCollection><s:memberList r:parseType="Collection"><s:Concept r:about="id:dmvi:d2e7484" r:label="religious services"/><s:Concept r:about="id:dmvi:d2e7490" r:label="religious concepts"><s:narrower><s:orderedCollection><s:memberList r:parseType="Collection"><s:Concept r:about="id:dmvi:d2e7549" r:label="pilgrimage"/></s:memberList></s:orderedCollection></s:narrower></s:Concept><s:Concept r:about="id:dmvi:d2e7579" r:label="Christianity"><s:narrower><s:orderedCollection><s:memberList r:parseType="Collection"><s:Concept r:about="id:dmvi:d2e7590" r:label="Protestantism"/></s:memberList></s:orderedCollection></s:narrower></s:Concept><s:Concept r:about="id:dmvi:d2e7632" r:label="festivals and feast days"><s:narrower><s:orderedCollection><s:memberList r:parseType="Collection"><s:Concept r:about="id:dmvi:d2e7634" r:label="Christmas"/></s:memberList></s:orderedCollection></s:narrower></s:Concept></s:memberList></s:orderedCollection></s:narrower></s:Concept><s:Concept r:about="id:dmvi:d2e7687" r:label="narrative themes"><s:narrower><s:orderedCollection><s:memberList r:parseType="Collection"><s:Concept r:about="id:dmvi:d2e7707" r:label="abstract concepts"><s:narrower><s:orderedCollection><s:memberList r:parseType="Collection"><s:Concept r:about="id:dmvi:d2e7709" r:label="anthropomorphism"/></s:memberList></s:orderedCollection></s:narrower></s:Concept><s:Concept r:about="id:dmvi:d2e7788" r:label="myths and stories"><s:narrower><s:orderedCollection><s:memberList r:parseType="Collection"><s:Concept r:about="id:dmvi:d2e7798" r:label="biblical legends"/><s:Concept r:about="id:dmvi:d2e7822" r:label="folktales and fairy tales"/><s:Concept r:about="id:dmvi:d2e7847" r:label="Shakespeare's plays"/></s:memberList></s:orderedCollection></s:narrower></s:Concept><s:Concept r:about="id:dmvi:d2e7853" r:label="wars and battles"><s:narrower><s:orderedCollection><s:memberList r:parseType="Collection"><s:Concept r:about="id:dmvi:d2e7895" r:label="Napoleonic Wars"/></s:memberList></s:orderedCollection></s:narrower></s:Concept><s:Concept r:about="id:dmvi:d2e7909" r:label="narrative events"><s:narrower><s:orderedCollection><s:memberList r:parseType="Collection"><s:Concept r:about="id:dmvi:d2e7944" r:label="danger"/></s:memberList></s:orderedCollection></s:narrower></s:Concept></s:memberList></s:orderedCollection></s:narrower></s:Concept></s:memberList></s:orderedCollection></s:narrower></s:Concept></r:RDF>